tvchannellist/__init__.py
tvchannellist/__version__.py
tvchannellist/channel.py
tvchannellist/engine.py
tvchannellist/engines/__init__.py
tvchannellist/engines/fi.py
tvchannellist/engines/it.py
tvchannellist/engines/us.py
tvchannellist-0.2.1.data/scripts/channellist
tvchannellist-0.2.1.dist-info/AUTHORS.md
tvchannellist-0.2.1.dist-info/LICENSE
tvchannellist-0.2.1.dist-info/METADATA
tvchannellist-0.2.1.dist-info/WHEEL
tvchannellist-0.2.1.dist-info/top_level.txt
tvchannellist-0.2.1.dist-info/RECORD
