Metadata-Version: 2.1
Name: tvchannellist
Version: 0.2.1
Summary: Python Package for programmatically retrieving LCN of television channels.
Home-page: https://github.com/tulindo/tvchannellist
Author: Paolo Tuninetto
Author-email: paolo.tuninetto@gmail.com
License: UNKNOWN
Platform: UNKNOWN
Classifier: Programming Language :: Python :: 3
Classifier: License :: OSI Approved :: GNU General Public License v3 (GPLv3)
Classifier: Operating System :: OS Independent
Classifier: Development Status :: 3 - Alpha
Requires-Python: >=3.7
Requires-Dist: requests
